practicepip/practicepip.py
practicepip-0.0.1.dist-info/LICENSE
practicepip-0.0.1.dist-info/METADATA
practicepip-0.0.1.dist-info/WHEEL
practicepip-0.0.1.dist-info/top_level.txt
practicepip-0.0.1.dist-info/RECORD
