Metadata-Version: 2.1
Name: practicepip
Version: 0.0.1
Summary: for practice making packages with pip
Classifier: Programming Language :: Python :: 3
License-File: LICENSE
